ltcv/__init__.py
ltcv/test.py
ltcv-0.0.0.2.dist-info/LICENSE
ltcv-0.0.0.2.dist-info/METADATA
ltcv-0.0.0.2.dist-info/WHEEL
ltcv-0.0.0.2.dist-info/top_level.txt
ltcv-0.0.0.2.dist-info/RECORD
