Metadata-Version: 2.1
Name: ltcv
Version: 0.0.0.2
Summary: CV Toolkit
Home-page: UNKNOWN
Author: Li Tao
Author-email: 1579776260@qq.com
License: UNKNOWN
Platform: UNKNOWN
Classifier: Programming Language :: Python :: 3
Classifier: License :: OSI Approved :: MIT License
Classifier: Operating System :: OS Independent
Requires-Python: >=3.0
